zbookmarks/__init__.py
zbookmarks/bookmark.py
zbookmarks-1.3.dist-info/LICENSE
zbookmarks-1.3.dist-info/WHEEL
zbookmarks-1.3.dist-info/METADATA
zbookmarks-1.3.dist-info/RECORD
