Metadata-Version: 2.1
Name: zbookmarks
Version: 1.3
Summary: Load / dump Chrome bookmark files
License: Apache-2.0
Author: Yannis Zarkadas
Requires-Python: >=3.6
Classifier: License :: OSI Approved :: Apache Software License
Classifier: Programming Language :: Python :: 3
Classifier: Programming Language :: Python :: 3.6
Classifier: Programming Language :: Python :: 3.7
Classifier: Programming Language :: Python :: 3.8
Classifier: Programming Language :: Python :: 3.9
Requires-Dist: beautifulsoup4 (>=4.9.3,<5.0.0)
Project-URL: Bug Tracker, https://github.com/yanniszark/zbookmarks/issues
Project-URL: documentation, https://github.com/yanniszark/zbookmarks/blob/master/README.md
Project-URL: homepage, https://github.com/yanniszark/zbookmarks
Project-URL: repository, https://github.com/yanniszark/zbookmarks
